quickscale_core/__init__.py
quickscale_core/_version.py
quickscale_core/config/__init__.py
quickscale_core/config/module_config.py
quickscale_core/context_processors.py
quickscale_core/generator/__init__.py
quickscale_core/generator/generator.py
quickscale_core/generator/templates/.dockerignore.j2
quickscale_core/generator/templates/.editorconfig.j2
quickscale_core/generator/templates/.env.example.j2
quickscale_core/generator/templates/.gitignore.j2
quickscale_core/generator/templates/.pre-commit-config.yaml.j2
quickscale_core/generator/templates/Dockerfile.j2
quickscale_core/generator/templates/README.md.j2
quickscale_core/generator/templates/docker-compose.yml.j2
quickscale_core/generator/templates/github/workflows/ci.yml.j2
quickscale_core/generator/templates/manage.py.j2
quickscale_core/generator/templates/project_name/__init__.py.j2
quickscale_core/generator/templates/project_name/asgi.py.j2
quickscale_core/generator/templates/project_name/context_processors.py.j2
quickscale_core/generator/templates/project_name/settings/__init__.py.j2
quickscale_core/generator/templates/project_name/settings/base.py.j2
quickscale_core/generator/templates/project_name/settings/local.py.j2
quickscale_core/generator/templates/project_name/settings/production.py.j2
quickscale_core/generator/templates/project_name/urls.py.j2
quickscale_core/generator/templates/project_name/views.py.j2
quickscale_core/generator/templates/project_name/wsgi.py.j2
quickscale_core/generator/templates/pyproject.toml.j2
quickscale_core/generator/templates/railway.json.j2
quickscale_core/generator/templates/start.sh.j2
quickscale_core/generator/templates/static/css/style.css.j2
quickscale_core/generator/templates/static/images/.gitkeep
quickscale_core/generator/templates/static/images/favicon.svg.j2
quickscale_core/generator/templates/static/js/.gitkeep
quickscale_core/generator/templates/templates/404.html.j2
quickscale_core/generator/templates/templates/500.html.j2
quickscale_core-0.73.0.dist-info/METADATA
quickscale_core-0.73.0.dist-info/WHEEL
quickscale_core-0.73.0.dist-info/RECORD
