Metadata-Version: 2.4
Name: quickscale-core
Version: 0.73.0
Summary: Core scaffolding and utilities for QuickScale Django project generator
License: Apache-2.0
Keywords: django,scaffolding,project-generator,saas
Author: Experto AI
Author-email: victor@experto.ai
Requires-Python: >=3.12,<4.0
Classifier: Development Status :: 3 - Alpha
Classifier: Framework :: Django
Classifier: Framework :: Django :: 6.0
Classifier: Intended Audience :: Developers
Classifier: License :: OSI Approved :: Apache Software License
Classifier: Programming Language :: Python :: 3
Classifier: Programming Language :: Python :: 3.12
Classifier: Programming Language :: Python :: 3.13
Classifier: Programming Language :: Python :: 3.14
Requires-Dist: Jinja2 (>=3.1.6,<4.0.0)
Requires-Dist: pyyaml (>=6.0.0,<7.0.0)
Project-URL: Documentation, https://github.com/Experto-AI/quickscale/tree/main/docs
Project-URL: Homepage, https://github.com/Experto-AI/quickscale
Project-URL: Repository, https://github.com/Experto-AI/quickscale
